botkit/__init__.py
botkit/botkit_modules/__init__.py
botkit/botkit_modules/module_manager/__init__.py
botkit/botkit_modules/module_manager/paged_module_view.py
botkit/botkit_modules/module_manager/pagination_model.py
botkit/botkit_modules/module_manager/view_models.py
botkit/botkit_modules/system/__init__.py
botkit/botkit_modules/system/status_pings.py
botkit/botkit_modules/system/system_tests.py
botkit/botkit_modules/system/sytem_management_module.py
botkit/botkit_services/__init__.py
botkit/botkit_services/bettermarkdown/__init__.py
botkit/botkit_services/bettermarkdown/_base.py
botkit/botkit_services/bettermarkdown/aliases.py
botkit/botkit_services/bettermarkdown/bettermarkdown.py
botkit/botkit_services/bettermarkdown/bettermarkdown_old.py
botkit/botkit_services/bettermarkdown/bettermarkdownlexer.py
botkit/botkit_services/bettermarkdown/config.py
botkit/botkit_services/bettermarkdown/markdownservice.py
botkit/botkit_services/botautomation/__init__.py
botkit/botkit_services/botautomation/base.py
botkit/botkit_services/botautomation/idletownbot.py
botkit/botkit_services/botautomation/stickerfinderbot.py
botkit/botkit_services/botautomation/stickeroptimizerbot.py
botkit/botkit_services/botautomation/stickersbot.py
botkit/botkit_services/botautomation/toolkitbot.py
botkit/botkit_services/botautomation/workingdictbot.py
botkit/botkit_services/eventing/__init__.py
botkit/botkit_services/eventing/botkit_event_bus.py
botkit/botkit_services/lookupservice.py
botkit/botkit_services/nlu/__init__.py
botkit/botkit_services/nlu/dialogflowconfig.py
botkit/botkit_services/nlu/messageunderstanding.py
botkit/botkit_services/nlu/nluservice.py
botkit/botkit_services/options/__init__.py
botkit/botkit_services/options/base.py
botkit/botkit_services/services.py
botkit/botkit_services/sr/__init__.py
botkit/botkit_services/sr/speechrecognition.py
botkit/builders/__init__.py
botkit/builders/htmlbuilder.py
botkit/builders/inlinemenubuilder.py
botkit/builders/metabuilder.py
autogram_botkit-0.2.0.dist-info/LICENSE
autogram_botkit-0.2.0.dist-info/WHEEL
autogram_botkit-0.2.0.dist-info/METADATA
autogram_botkit-0.2.0.dist-info/RECORD
