Metadata-Version: 2.1
Name: autogram-botkit
Version: 0.2.0
Summary: 
Author: JosXa
Requires-Python: >=3.8,<4.0
Classifier: Programming Language :: Python :: 3
Classifier: Programming Language :: Python :: 3.8
Requires-Dist: boltons (>=20.1.0,<21.0.0)
Requires-Dist: buslane (>=0.0.u,<0.1)
Requires-Dist: cached_property (>=1.5.1,<2.0.0)
Requires-Dist: decorators (>=0.1.1,<0.2.0)
Requires-Dist: haps (>=1.1.2,<2.0.0)
Requires-Dist: logzero
Requires-Dist: more-itertools (>=8.2.0,<9.0.0)
Requires-Dist: ordered_set (>=3.1.1,<4.0.0)
Requires-Dist: pydantic[dotenv] (>=1.4,<2.0)
Requires-Dist: pyhumps (>=1.3.1,<2.0.0)
Requires-Dist: python-decouple (==3.3)
Requires-Dist: pytz (==2020.1)
Requires-Dist: redis-collections (>=0.8.1,<0.9.0)
Requires-Dist: tgcrypto (>=1.2.0,<2.0.0)
Requires-Dist: typing-inspect (>=0.5.0,<0.6.0)
Requires-Dist: unsync (>=1.2.1,<2.0.0)
